mocp_cli/__init__.py
mocp_cli/player.py
mocp_cli/scripts/__init__.py
mocp_cli/scripts/player.py
mocp_cli-0.1.22.dist-info/LICENSE.txt
mocp_cli-0.1.22.dist-info/METADATA
mocp_cli-0.1.22.dist-info/WHEEL
mocp_cli-0.1.22.dist-info/entry_points.txt
mocp_cli-0.1.22.dist-info/top_level.txt
mocp_cli-0.1.22.dist-info/RECORD
