Metadata-Version: 2.1
Name: mocp-cli
Version: 0.1.22
Summary: CLI tools for finding, organizing, and playing audio files
Home-page: https://github.com/kenjyco/mocp-cli
Author: Ken
Author-email: kenjyco@gmail.com
License: MIT
Download-URL: https://github.com/kenjyco/mocp-cli/tarball/v0.1.22
Keywords: moc,mocp,cli,command-line,console audio,repl,mp3 player,kenjyco
Platform: UNKNOWN
Classifier: Development Status :: 3 - Alpha
Classifier: Environment :: Console
Classifier: Intended Audience :: Developers
Classifier: License :: OSI Approved :: MIT License
Classifier: Operating System :: MacOS :: MacOS X
Classifier: Operating System :: POSIX :: Linux
Classifier: Programming Language :: Python :: 3.5
Classifier: Programming Language :: Python
Classifier: Topic :: Multimedia :: Sound/Audio :: Players
Classifier: Topic :: Software Development :: Libraries
Requires-Dist: bg-helper
Requires-Dist: chloop
Requires-Dist: click >=6.0
Requires-Dist: input-helper
Requires-Dist: mocp
Provides-Extra: extras
Requires-Dist: mocp[extras] ; extra == 'extras'
